README.md
setup.py
reqtools/__init__.py
reqtools/sessions.py
reqtools.egg-info/PKG-INFO
reqtools.egg-info/SOURCES.txt
reqtools.egg-info/dependency_links.txt
reqtools.egg-info/not-zip-safe
reqtools.egg-info/requires.txt
reqtools.egg-info/top_level.txt