Metadata-Version: 1.1
Name: reqtools
Version: 0.0.5
Summary: Extension for requests library
Home-page: https://github.com/oztqa/reqtools
Author: UNKNOWN
Author-email: UNKNOWN
License: UNKNOWN
Platform: any
Classifier: Development Status :: 4 - Beta
Classifier: Natural Language :: Russian
Classifier: Intended Audience :: Developers
Classifier: Operating System :: OS Independent
Classifier: Programming Language :: Python :: 3
Classifier: Programming Language :: Python :: Implementation :: CPython
